{
  "policy": null,
  "log": {
    "access": "",
    "error": "",
    "loglevel": "warning"
  },
  "inbounds": [
    {
      "tag": "proxy",
      "port": 10917,
      "listen": "0.0.0.0",
      "protocol": "socks",
      "sniffing": {
        "enabled": true,
        "destOverride": [
          "http",
          "tls"
        ]
      },
      "settings": {
        "auth": "noauth",
        "udp": true,
        "ip": null,
        "address": null,
        "clients": null,
        "decryption": null
      },
      "streamSettings": null
    }
  ],
  "outbounds": [
    {
      "tag": "proxy",
      "protocol": "vmess",
      "settings": {
        "vnext": [
          {
            "address": "104.21.79.143",
            "port": 80,
            "users": [
              {
                "id": "8b745f74-c322-48c0-b27c-cb6a1d871e86",
                "alterId": 0,
                "email": "",
                "security": "auto",
                "encryption": null,
                "flow": null
              }
            ]
          }
        ],
        "servers": null,
        "response": null
      },
      "streamSettings": {
        "network": "ws",
        "security": null,
        "tlsSettings": null,
        "tcpSettings": null,
        "kcpSettings": null,
        "wsSettings": {
          "connectionReuse": true,
          "path": "ae8e857abf1d?ed=2048",
          "headers": {
            "Host": "periodically-microwave-firms-abc.trycloudflare.com"
          }
        },
        "httpSettings": null,
        "quicSettings": null,
        "xtlsSettings": null
      },
      "mux": {
        "enabled": false,
        "concurrency": -1
      }
    },
    {
      "tag": "direct",
      "protocol": "freedom",
      "settings": {
        "vnext": null,
        "servers": null,
        "response": null
      },
      "streamSettings": null,
      "mux": null
    },
    {
      "tag": "block",
      "protocol": "blackhole",
      "settings": {
        "vnext": null,
        "servers": null,
        "response": {
          "type": "http"
        }
      },
      "streamSettings": null,
      "mux": null
    }
  ],
  "stats": null,
  "api": null,
  "dns": null,
  "routing": {
    "domainStrategy": "IPIfNonMatch",
    "rules": [
      {
        "type": "field",
        "port": null,
        "inboundTag": [
          "api"
        ],
        "outboundTag": "api",
        "ip": null,
        "domain": null
      }
    ]
  }
}